[{"model": "people.person", "pk": 1, "fields": {"surname": "Marcato", "rank": "Senior", "user": 1, "mobile_phone": "+393406639481", "office": "Padova", "avatar": "https://cdn0.iconfinder.com/data/icons/avatars-3/512/avatar_bussiness_man-256.png"}}, {"model": "people.person", "pk": 2, "fields": {"surname": "Fecchio", "rank": "Senior", "user": 2, "mobile_phone": "+393406639482", "office": "Padova", "avatar": "http://senacultural.com/wp-content/uploads/2015/03/avatar.png"}}, {"model": "people.person", "pk": 3, "fields": {"surname": "Celli", "rank": "Senior", "user": 3, "mobile_phone": "+393406639483", "office": "Padova", "avatar": "http://faabpharma.com/img/avatar.png"}}, {"model": "people.person", "pk": 4, "fields": {"surname": "Giust", "rank": "Consultant", "user": 4, "mobile_phone": "+393406639484", "office": "Padova", "avatar": "https://cdn0.iconfinder.com/data/icons/avatars-3/512/avatar_smart_guy-512.png"}}, {"model": "people.person", "pk": 5, "fields": {"surname": "Russo", "rank": "Assistant Manager", "user": 5, "mobile_phone": "+393406639484", "office": "Padova", "avatar": "https://s-media-cache-ak0.pinimg.com/564x/77/c9/b9/77c9b909571b386fce2f4f2dde320b4f.jpg"}}, {"model": "people.person", "pk": 6, "fields": {"surname": "Zanetti", "rank": "Consultant", "user": 6, "mobile_phone": "+393406639485", "office": "Verona", "avatar": "http://www.justdoxit.com/new2/wp-content/uploads/2015/11/avatar_working_girl-512.png"}}]